invenio_rdm_migrator/__init__.py
invenio_rdm_migrator/logging.py
invenio_rdm_migrator/state.py
invenio_rdm_migrator/testutils.py
invenio_rdm_migrator/utils.py
invenio_rdm_migrator/actions/__init__.py
invenio_rdm_migrator/actions/base.py
invenio_rdm_migrator/extract/__init__.py
invenio_rdm_migrator/extract/base.py
invenio_rdm_migrator/extract/jsonlines.py
invenio_rdm_migrator/extract/null.py
invenio_rdm_migrator/extract/transactions.py
invenio_rdm_migrator/load/__init__.py
invenio_rdm_migrator/load/base.py
invenio_rdm_migrator/load/ids.py
invenio_rdm_migrator/load/postgresql/__init__.py
invenio_rdm_migrator/load/postgresql/generators.py
invenio_rdm_migrator/load/postgresql/models.py
invenio_rdm_migrator/load/postgresql/sequences.py
invenio_rdm_migrator/load/postgresql/bulk/__init__.py
invenio_rdm_migrator/load/postgresql/bulk/copy.py
invenio_rdm_migrator/load/postgresql/bulk/generators/__init__.py
invenio_rdm_migrator/load/postgresql/bulk/generators/existing.py
invenio_rdm_migrator/load/postgresql/bulk/generators/single.py
invenio_rdm_migrator/load/postgresql/bulk/generators/table.py
invenio_rdm_migrator/load/postgresql/transactions/__init__.py
invenio_rdm_migrator/load/postgresql/transactions/errors.py
invenio_rdm_migrator/load/postgresql/transactions/execute.py
invenio_rdm_migrator/load/postgresql/transactions/operations.py
invenio_rdm_migrator/streams/__init__.py
invenio_rdm_migrator/streams/runner.py
invenio_rdm_migrator/streams/streams.py
invenio_rdm_migrator/streams/actions/__init__.py
invenio_rdm_migrator/streams/actions/load/__init__.py
invenio_rdm_migrator/streams/actions/load/communities.py
invenio_rdm_migrator/streams/actions/load/drafts.py
invenio_rdm_migrator/streams/actions/load/files.py
invenio_rdm_migrator/streams/actions/load/ignored.py
invenio_rdm_migrator/streams/actions/load/parents.py
invenio_rdm_migrator/streams/actions/load/users.py
invenio_rdm_migrator/streams/actions/load/github/__init__.py
invenio_rdm_migrator-5.0.0.dist-info/AUTHORS.rst
invenio_rdm_migrator-5.0.0.dist-info/LICENSE
invenio_rdm_migrator-5.0.0.dist-info/METADATA
invenio_rdm_migrator-5.0.0.dist-info/WHEEL
invenio_rdm_migrator-5.0.0.dist-info/top_level.txt
invenio_rdm_migrator-5.0.0.dist-info/RECORD
