Metadata-Version: 2.1
Name: invenio-rdm-migrator
Version: 5.0.0
Summary: InvenioRDM module for data migration.
Home-page: https://github.com/inveniosoftware/invenio-rdm-migrator
Author: CERN
Author-email: info@inveniosoftware.org
License: MIT
Keywords: invenio rdm migration
Platform: any
Classifier: Development Status :: 3 - Alpha
Requires-Python: >=3.7
Requires-Dist: pypeln >=0.4.9
Requires-Dist: orjson >=3.9.5
Requires-Dist: jsonlines >=3.1.0
Requires-Dist: psycopg >=3.1.9
Requires-Dist: python-json-logger >=2.0.7
Requires-Dist: PyYAML >=5.4.1
Provides-Extra: alchemy
Requires-Dist: sqlalchemy >=2.0 ; extra == 'alchemy'
Requires-Dist: sqlalchemy-utils[encrypted] >=0.38.3 ; extra == 'alchemy'
Provides-Extra: tests
Requires-Dist: dictdiffer >=0.9.0 ; extra == 'tests'
Requires-Dist: pytest-black >=0.3.0 ; extra == 'tests'
Requires-Dist: pytest-invenio <3.0.0,>=2.1.0 ; extra == 'tests'
Requires-Dist: pytest-mock >=1.6.0 ; extra == 'tests'
